WeiXueyuanNginxJiaochengFix1/README.md
WeiXueyuanNginxJiaochengFix1/__init__.py
WeiXueyuanNginxJiaochengFix1/__main__.py
WeiXueyuanNginxJiaochengFix1/file.epub
WeiXueyuanNginxJiaochengFix1/index.html
WeiXueyuanNginxJiaochengFix1/css/__init__.py
WeiXueyuanNginxJiaochengFix1/css/annotations.css
WeiXueyuanNginxJiaochengFix1/css/main.css
WeiXueyuanNginxJiaochengFix1/css/normalize.css
WeiXueyuanNginxJiaochengFix1/css/popup.css
WeiXueyuanNginxJiaochengFix1/font/__init__.py
WeiXueyuanNginxJiaochengFix1/font/fontello.eot
WeiXueyuanNginxJiaochengFix1/font/fontello.svg
WeiXueyuanNginxJiaochengFix1/font/fontello.ttf
WeiXueyuanNginxJiaochengFix1/font/fontello.woff
WeiXueyuanNginxJiaochengFix1/img/__init__.py
WeiXueyuanNginxJiaochengFix1/img/annotator-glyph-sprite.png
WeiXueyuanNginxJiaochengFix1/img/annotator-icon-sprite.png
WeiXueyuanNginxJiaochengFix1/img/apple-touch-icon.png
WeiXueyuanNginxJiaochengFix1/img/cancelfullscreen.png
WeiXueyuanNginxJiaochengFix1/img/close.png
WeiXueyuanNginxJiaochengFix1/img/fullscreen.png
WeiXueyuanNginxJiaochengFix1/img/loader.gif
WeiXueyuanNginxJiaochengFix1/img/menu-icon.png
WeiXueyuanNginxJiaochengFix1/img/save.png
WeiXueyuanNginxJiaochengFix1/img/saved.png
WeiXueyuanNginxJiaochengFix1/img/settings-s.png
WeiXueyuanNginxJiaochengFix1/img/settings.png
WeiXueyuanNginxJiaochengFix1/img/star.png
WeiXueyuanNginxJiaochengFix1/js/__init__.py
WeiXueyuanNginxJiaochengFix1/js/epub.js
WeiXueyuanNginxJiaochengFix1/js/epub.min.js
WeiXueyuanNginxJiaochengFix1/js/epub.min.map
WeiXueyuanNginxJiaochengFix1/js/hooks.min.js
WeiXueyuanNginxJiaochengFix1/js/hooks.min.map
WeiXueyuanNginxJiaochengFix1/js/reader.js
WeiXueyuanNginxJiaochengFix1/js/reader.js.map
WeiXueyuanNginxJiaochengFix1/js/reader.min.js
WeiXueyuanNginxJiaochengFix1/js/reader.min.map
WeiXueyuanNginxJiaochengFix1/js/hooks/__init__.py
WeiXueyuanNginxJiaochengFix1/js/hooks/extensions/__init__.py
WeiXueyuanNginxJiaochengFix1/js/hooks/extensions/highlight.js
wei_xueyuan_nginx_jiaocheng_fix1-2025.3.25.0.dist-info/METADATA
wei_xueyuan_nginx_jiaocheng_fix1-2025.3.25.0.dist-info/WHEEL
wei_xueyuan_nginx_jiaocheng_fix1-2025.3.25.0.dist-info/entry_points.txt
wei_xueyuan_nginx_jiaocheng_fix1-2025.3.25.0.dist-info/top_level.txt
wei_xueyuan_nginx_jiaocheng_fix1-2025.3.25.0.dist-info/RECORD
